LICENSE
MANIFEST.in
README.md
requirements.txt
setup.cfg
setup.py
docker_registry/__init__.py
docker_registry/drivers/__init__.py
docker_registry/drivers/elliptics.py
docker_registry_driver_elliptics.egg-info/PKG-INFO
docker_registry_driver_elliptics.egg-info/SOURCES.txt
docker_registry_driver_elliptics.egg-info/dependency_links.txt
docker_registry_driver_elliptics.egg-info/namespace_packages.txt
docker_registry_driver_elliptics.egg-info/not-zip-safe
docker_registry_driver_elliptics.egg-info/requires.txt
docker_registry_driver_elliptics.egg-info/top_level.txt
tests/requirements.txt