Metadata-Version: 1.1
Name: docker-registry-driver-elliptics
Version: 0.0.3
Summary: Docker registry elliptics driver
Home-page: https://github.com/noxiouz/docker-registry-driver-elliptics
Author: Anton Tiurin
Author-email: noxiouz@yandex.ru
License: 
